Metadata-Version: 2.1
Name: dataclasses-jsonschema-rereleased
Version: 2.12.2
Summary: JSON schema generation from dataclasses
Home-page: https://github.com/s-knibbs/dataclasses-jsonschema
Author: Simon Knibbs
Author-email: simon.knibbs@gmail.com
License: MIT
Platform: UNKNOWN
Classifier: Development Status :: 4 - Beta
Classifier: Intended Audience :: Developers
Classifier: License :: OSI Approved :: MIT License
Classifier: Programming Language :: Python
Classifier: Programming Language :: Python :: 3.6
Classifier: Programming Language :: Python :: 3.7
Classifier: Topic :: Software Development :: Libraries
Requires-Dist: python-dateutil
Requires-Dist: jsonschema
Requires-Dist: mypy-extensions
Requires-Dist: typing-extensions
Requires-Dist: dataclasses ; python_version < "3.7"
Provides-Extra: apispec
Requires-Dist: apispec (==3.3.2) ; extra == 'apispec'
Provides-Extra: fast-validation
Requires-Dist: fastjsonschema (==2.14.5) ; extra == 'fast-validation'
